odoo/addons/product_listprice_currency/LICENSE
odoo/addons/product_listprice_currency/README.rst
odoo/addons/product_listprice_currency/__init__.py
odoo/addons/product_listprice_currency/__manifest__.py
odoo/addons/product_listprice_currency/images/screen.png
odoo/addons/product_listprice_currency/models/__init__.py
odoo/addons/product_listprice_currency/models/product_template.py
odoo/addons/product_listprice_currency/static/description/icon.png
odoo/addons/product_listprice_currency/static/description/index.html
odoo/addons/product_listprice_currency/tests/TEST_INSTRUCTIONS.rst
odoo/addons/product_listprice_currency/views/product_template.xml
odoo_addon_product_listprice_currency-16.0.1.0.0.dist-info/METADATA
odoo_addon_product_listprice_currency-16.0.1.0.0.dist-info/WHEEL
odoo_addon_product_listprice_currency-16.0.1.0.0.dist-info/top_level.txt
odoo_addon_product_listprice_currency-16.0.1.0.0.dist-info/RECORD
